qie/__init__.py
qie-1.0.1.dist-info/LICENSE.txt
qie-1.0.1.dist-info/METADATA
qie-1.0.1.dist-info/WHEEL
qie-1.0.1.dist-info/top_level.txt
qie-1.0.1.dist-info/RECORD
