Metadata-Version: 2.1
Name: qie
Version: 1.0.1
Summary: A tool for quickly importing every modules installed in the current environment.
Home-page: https://github.com/wjz-space/qie
Author: 街角的猫_wjz
Author-email: wjz-space@outlook.com
Classifier: Programming Language :: Python :: 3
Classifier: License :: OSI Approved :: MIT License
Classifier: Operating System :: OS Independent
Requires-Python: >=3.0
License-File: LICENSE.txt
